_canary/__init__.py
_canary/atc.py
_canary/enums.py
_canary/error.py
_canary/expression.py
_canary/finder.py
_canary/generator.py
_canary/main.py
_canary/paramset.py
_canary/py.typed
_canary/queue.py
_canary/session.py
_canary/status.py
_canary/testcase.py
_canary/testinstance.py
_canary/version.py
_canary/when.py
_canary/config/__init__.py
_canary/config/_machine.py
_canary/config/argparsing.py
_canary/config/config.py
_canary/config/linux.py
_canary/config/macos.py
_canary/config/rpool.py
_canary/config/schemas.py
_canary/plugins/__init__.py
_canary/plugins/hookspec.py
_canary/plugins/manager.py
_canary/plugins/types.py
_canary/plugins/builtin/__init__.py
_canary/plugins/builtin/discover.py
_canary/plugins/builtin/email.py
_canary/plugins/builtin/html.py
_canary/plugins/builtin/json.py
_canary/plugins/builtin/junit.py
_canary/plugins/builtin/markdown.py
_canary/plugins/builtin/mask.py
_canary/plugins/builtin/oversubscribe.py
_canary/plugins/builtin/post_clean.py
_canary/plugins/builtin/pyt.py
_canary/plugins/builtin/repeat.py
_canary/plugins/builtin/reporting.py
_canary/plugins/builtin/resource.py
_canary/plugins/builtin/runtest_protocol.py
_canary/plugins/builtin/runtests.py
_canary/plugins/builtin/testcase_generator.py
_canary/plugins/subcommands/__init__.py
_canary/plugins/subcommands/autodoc.py
_canary/plugins/subcommands/check.py
_canary/plugins/subcommands/config.py
_canary/plugins/subcommands/describe.py
_canary/plugins/subcommands/docs.py
_canary/plugins/subcommands/edit.py
_canary/plugins/subcommands/fetch.py
_canary/plugins/subcommands/find.py
_canary/plugins/subcommands/help.py
_canary/plugins/subcommands/info.py
_canary/plugins/subcommands/location.py
_canary/plugins/subcommands/log.py
_canary/plugins/subcommands/rebaseline.py
_canary/plugins/subcommands/report.py
_canary/plugins/subcommands/run.py
_canary/plugins/subcommands/status.py
_canary/plugins/subcommands/tree.py
_canary/plugins/subcommands/common/__init__.py
canary_wm-25.10.7.dist-info/licenses/AUTHORS
canary_wm-25.10.7.dist-info/licenses/LICENSE
canary_wm-25.10.7.dist-info/METADATA
canary_wm-25.10.7.dist-info/WHEEL
canary_wm-25.10.7.dist-info/entry_points.txt
canary_wm-25.10.7.dist-info/top_level.txt
canary_wm-25.10.7.dist-info/RECORD
