Metadata-Version: 2.4
Name: canary-wm
Version: 25.10.7
Summary: canary: application testing with Python
Author: Tim Fuller, Others (See AUTHORS)
License: Copyright 2025 National Technology & Engineering Solutions of Sandia, LLC (NTESS). Under the terms
Project-URL: Documentation, https://canary-wm.readthedocs.io/en/production/
Project-URL: Issues, https://github.com/sandialabs/canary/issues
Project-URL: Repository, https://github.com/sandialabs/canary
Keywords: test,unittest
Classifier: Development Status :: 6 - Mature
Classifier: Intended Audience :: Developers
Classifier: License :: OSI Approved :: MIT License
Classifier: Operating System :: MacOS
Classifier: Operating System :: Microsoft :: Windows
Classifier: Operating System :: POSIX
Classifier: Operating System :: Unix
Classifier: Programming Language :: Python :: 3 :: Only
Classifier: Programming Language :: Python :: 3.10
Classifier: Programming Language :: Python :: 3.11
Classifier: Programming Language :: Python :: 3.12
Classifier: Programming Language :: Python :: 3.13
Classifier: Programming Language :: Python :: 3.14
Classifier: Topic :: Software Development :: Libraries
Classifier: Topic :: Software Development :: Testing
Classifier: Topic :: Utilities
Requires-Python: >=3.10
License-File: LICENSE
License-File: AUTHORS
Requires-Dist: hpc-connect==25.10.7
Requires-Dist: pluggy>=1.5
Requires-Dist: psutil
Requires-Dist: pyyaml
Requires-Dist: schema
Provides-Extra: dev
Requires-Dist: coverage; extra == "dev"
Requires-Dist: mypy; extra == "dev"
Requires-Dist: pydata-sphinx-theme; extra == "dev"
Requires-Dist: pytest; extra == "dev"
Requires-Dist: ruff; extra == "dev"
Requires-Dist: sphinx; extra == "dev"
Requires-Dist: sphinx-design; extra == "dev"
Requires-Dist: xmlschema; extra == "dev"
Provides-Extra: flux
Provides-Extra: pbs
Provides-Extra: psutil
Provides-Extra: requests
Requires-Dist: requests; extra == "requests"
Provides-Extra: slurm
Dynamic: license-file
